odoo/addons/base_cron_exclusion/README.rst
odoo/addons/base_cron_exclusion/__init__.py
odoo/addons/base_cron_exclusion/__manifest__.py
odoo/addons/base_cron_exclusion/i18n/base_cron_exclusion.pot
odoo/addons/base_cron_exclusion/i18n/cs_CZ.po
odoo/addons/base_cron_exclusion/i18n/es.po
odoo/addons/base_cron_exclusion/i18n/es_AR.po
odoo/addons/base_cron_exclusion/i18n/fr.po
odoo/addons/base_cron_exclusion/i18n/it.po
odoo/addons/base_cron_exclusion/i18n/zh_CN.po
odoo/addons/base_cron_exclusion/models/__init__.py
odoo/addons/base_cron_exclusion/models/ir_cron.py
odoo/addons/base_cron_exclusion/readme/CONTRIBUTORS.md
odoo/addons/base_cron_exclusion/readme/CREDITS.md
odoo/addons/base_cron_exclusion/readme/DESCRIPTION.md
odoo/addons/base_cron_exclusion/readme/USAGE.md
odoo/addons/base_cron_exclusion/static/description/icon.png
odoo/addons/base_cron_exclusion/static/description/index.html
odoo/addons/base_cron_exclusion/tests/__init__.py
odoo/addons/base_cron_exclusion/tests/test_ir_cron.py
odoo/addons/base_cron_exclusion/views/ir_cron_view.xml
odoo_addon_base_cron_exclusion-18.0.1.0.1.dist-info/METADATA
odoo_addon_base_cron_exclusion-18.0.1.0.1.dist-info/WHEEL
odoo_addon_base_cron_exclusion-18.0.1.0.1.dist-info/top_level.txt
odoo_addon_base_cron_exclusion-18.0.1.0.1.dist-info/RECORD
